dockenv/__init__.py
dockenv/dockenv.py
dockenv-0.1.3.dist-info/entry_points.txt
dockenv-0.1.3.dist-info/WHEEL
dockenv-0.1.3.dist-info/METADATA
dockenv-0.1.3.dist-info/RECORD
