Metadata-Version: 2.1
Name: dockenv
Version: 0.1.3
Summary: Simple cli utility for generate docker-compose.yml files
Author: t33m4h
Requires-Python: >=3.6,<4.0
Classifier: Programming Language :: Python :: 3
Classifier: Programming Language :: Python :: 3.6
Classifier: Programming Language :: Python :: 3.7
Requires-Dist: fire (>=0.2.1,<0.3.0)
Requires-Dist: loguru (>=0.3.2,<0.4.0)
Requires-Dist: pyyaml (>=5.1,<6.0)
